Pokelmgr/__init__.py
Pokelmgr/pokemon.csv
Pokelmgr/random_pokemon.py
Pokelmgr-1.0.0.dist-info/METADATA
Pokelmgr-1.0.0.dist-info/WHEEL
Pokelmgr-1.0.0.dist-info/top_level.txt
Pokelmgr-1.0.0.dist-info/RECORD
