Metadata-Version: 2.1
Name: Pokelmgr
Version: 1.0.0
Summary: Libreria para generar un Pokemon aleatoro.
Author: Luz Gonzalez
Author-email: 202224155_gonzalez@tesch.edu.mx
Requires-Dist: pandas
